<?xml version="1.0"?>

<ruleset name="Pronamic Domain Mapping">
	<rule ref="WordPress">
		<exclude name="Generic.WhiteSpace.ScopeIndent.Incorrect" />

		<exclude name="Squiz.Commenting" />

		<exclude name="WordPress.VIP.DirectDatabaseQuery" />
		<exclude name="WordPress.VIP.PostsPerPage.posts_per_page" />
		<exclude name="WordPress.VIP.SlowDBQuery.slow_db_query" />
		<exclude name="WordPress.VIP.SuperGlobalInputUsage.AccessDetected" />
		<exclude name="WordPress.VIP.ValidatedSanitizedInput" />
	</rule>
</ruleset>
